exoedge_opcua/__init__.py
exoedge_opcua/__version__.py
exoedge_opcua/lib.py
exoedge_opcua-1.0.0.dist-info/LICENSE.txt
exoedge_opcua-1.0.0.dist-info/METADATA
exoedge_opcua-1.0.0.dist-info/WHEEL
exoedge_opcua-1.0.0.dist-info/top_level.txt
exoedge_opcua-1.0.0.dist-info/RECORD
